brue/__init__.py
brue/__main__.py
brue/_core.py
brue/_utils.py
brue/decorators.py
brue/directives.py
brue/assets/script.js
brue/assets/template.zip
brue-2021.11.15.dist-info/LICENSE
brue-2021.11.15.dist-info/METADATA
brue-2021.11.15.dist-info/WHEEL
brue-2021.11.15.dist-info/entry_points.txt
brue-2021.11.15.dist-info/top_level.txt
brue-2021.11.15.dist-info/RECORD
