Metadata-Version: 2.1
Name: brue
Version: 2021.11.15
Summary: modern web gui using python
Home-page: https://github.com/eseunghwan/brue
Author: Lee Seung Hwan
Author-email: shlee0920@naver.com
License: MIT license
Platform: UNKNOWN
Requires-Python: >=3.7
License-File: LICENSE
Requires-Dist: javascripthon
Requires-Dist: minify-html
Requires-Dist: jsmin
